QBI_radon/__init__.py
QBI_radon/radon.py
QBI_radon/utils.py
qbi_radon-1.8.4.dist-info/LICENSE
qbi_radon-1.8.4.dist-info/METADATA
qbi_radon-1.8.4.dist-info/WHEEL
qbi_radon-1.8.4.dist-info/top_level.txt
qbi_radon-1.8.4.dist-info/RECORD
