Metadata-Version: 2.1
Name: qbi-radon
Version: 1.8.4
Summary: Radon Transformation for PyTorch 2
Author: Minh Nhat Trinh
Classifier: Intended Audience :: Science/Research
Classifier: Programming Language :: Python :: 3
Classifier: License :: OSI Approved :: GNU General Public License v3 (GPLv3)
Classifier: Operating System :: OS Independent
License-File: LICENSE
Provides-Extra: torch
Requires-Dist: torch >=2.0 ; extra == 'torch'
